CHANGES.rst
DESCRIPTION.rst
LICENSE
MANIFEST.in
README.md
setup.py
src/pypulseprofiles/__init__.py
src/pypulseprofiles/apply.py
src/pypulseprofiles/config.py
src/pypulseprofiles/core.py
src/pypulseprofiles/create.py
src/pypulseprofiles/delete.py
src/pypulseprofiles/info.py
src/pypulseprofiles/list.py
src/python_pulseaudio_profiles.egg-info/PKG-INFO
src/python_pulseaudio_profiles.egg-info/SOURCES.txt
src/python_pulseaudio_profiles.egg-info/dependency_links.txt
src/python_pulseaudio_profiles.egg-info/entry_points.txt
src/python_pulseaudio_profiles.egg-info/requires.txt
src/python_pulseaudio_profiles.egg-info/top_level.txt