Metadata-Version: 2.1
Name: python-pulseaudio-profiles
Version: 0.0.3
Summary: Simple library to create and apply pulseaudio profiles.
Home-page: https://github.com/fracpete/python-pulseaudio-profiles
Author: Peter "fracpete" Reutemann
Author-email: fracpete@gmail.com
License: MIT License
Platform: UNKNOWN
Classifier: Development Status :: 4 - Beta
Classifier: License :: OSI Approved :: MIT License
Classifier: Topic :: Multimedia :: Sound/Audio
Classifier: Programming Language :: Python :: 3
Classifier: Operating System :: POSIX :: Linux
License-File: LICENSE
